pyqt_autotest/__init__.py
pyqt_autotest/random_auto_test.py
pyqt_autotest/repeatable_auto_test.py
pyqt_autotest/cli/config.py
pyqt_autotest/cli/list_tests.py
pyqt_autotest/cli/main.py
pyqt_autotest/cli/modules.py
pyqt_autotest/cli/options.py
pyqt_autotest/cli/run_tests.py
pyqt_autotest/core/action.py
pyqt_autotest/core/auto_test.py
pyqt_autotest/core/exception_handler.py
pyqt_autotest/core/exceptions.py
pyqt_autotest/examples/complex/README.md
pyqt_autotest/examples/complex/__init__.py
pyqt_autotest/examples/complex/test.py
pyqt_autotest/examples/moderate/README.md
pyqt_autotest/examples/moderate/__init__.py
pyqt_autotest/examples/moderate/test.py
pyqt_autotest/examples/moderate/three-body-parameters.txt
pyqt_autotest/examples/repeatable/README.md
pyqt_autotest/examples/repeatable/__init__.py
pyqt_autotest/examples/repeatable/test.py
pyqt_autotest/examples/repeatable/usercode.py
pyqt_autotest/examples/simple/README.md
pyqt_autotest/examples/simple/__init__.py
pyqt_autotest/examples/simple/test.py
pyqt_autotest/examples/simple/usercode.py
pyqt_autotest/qt/__init__.py
pyqt_autotest/qt/application.py
pyqt_autotest/qt/modal_unblocker.py
pyqt_autotest/qt/top_level_widgets.py
pyqt_autotest/qt/widgets.py
pyqt_autotest/results/exit_state.py
pyqt_autotest/results/json_results_dict.py
pyqt_autotest/results/print_results.py
pyqt_autotest/results/result_schema.py
pyqt_autotest/results/statistic_finder.py
pyqt_autotest/utilities/__init__.py
pyqt_autotest/utilities/print_colors.py
pyqt_autotest/utilities/randomizer.py
pyqt_autotest/utilities/singleton.py
pyqt_autotest/utilities/verbosity_controller.py
pyqt_autotest-0.2.1.dist-info/LICENSE
pyqt_autotest-0.2.1.dist-info/METADATA
pyqt_autotest-0.2.1.dist-info/WHEEL
pyqt_autotest-0.2.1.dist-info/entry_points.txt
pyqt_autotest-0.2.1.dist-info/top_level.txt
pyqt_autotest-0.2.1.dist-info/RECORD
