Metadata-Version: 2.1
Name: pyqt-autotest
Version: 0.2.1
Summary: A command line tool for finding system-level bugs that cause a python Qt application to terminate.
Author-email: Robert Applin <robertapplin.developer@gmail.com>
License: GNU GENERAL PUBLIC LICENSE
Project-URL: Homepage, https://github.com/robertapplin/pyqt-autotest
Project-URL: Bug Tracker, https://github.com/robertapplin/pyqt-autotest/issues
Keywords: python,qt,random,auto,test
Classifier: Programming Language :: Python :: 3
Classifier: License :: OSI Approved :: GNU General Public License v3 (GPLv3)
Classifier: Operating System :: OS Independent
Requires-Python: >=3.7
License-File: LICENSE
Requires-Dist: PyQt5
Requires-Dist: schema
Requires-Dist: tqdm
